sqlax/__init__.py
sqlax/errors/__init__.py
sqlax/errors/exc.py
sqlax/manager/__init__.py
sqlax/manager/manager.py
sqlax/utils/__init__.py
sqlax/utils/base.py
sqlax/utils/service.py
sqla_x-1.1.3.dist-info/METADATA
sqla_x-1.1.3.dist-info/WHEEL
sqla_x-1.1.3.dist-info/top_level.txt
sqla_x-1.1.3.dist-info/RECORD
